psij/__init__.py
psij/__main__.py
psij/_plugins.py
psij/descriptor.py
psij/exceptions.py
psij/job.py
psij/job_attributes.py
psij/job_executor.py
psij/job_executor_config.py
psij/job_launcher.py
psij/job_spec.py
psij/job_state.py
psij/job_status.py
psij/launcher.py
psij/py.typed
psij/resource_spec.py
psij/serialize.py
psij/utils.py
psij/version.py
psij/executors/__init__.py
psij/executors/flux.py
psij/executors/local.py
psij/executors/rp.py
psij/executors/batch/__init__.py
psij/executors/batch/batch_scheduler_executor.py
psij/executors/batch/cobalt.py
psij/executors/batch/escape_functions.py
psij/executors/batch/lsf.py
psij/executors/batch/pbs.py
psij/executors/batch/pbs_base.py
psij/executors/batch/pbs_classic.py
psij/executors/batch/script_generator.py
psij/executors/batch/slurm.py
psij/executors/batch/template_function_library.py
psij/executors/batch/cobalt/cobalt.mustache
psij/executors/batch/lsf/lsf.mustache
psij/executors/batch/pbs/pbs_classic.mustache
psij/executors/batch/pbs/pbspro.mustache
psij/executors/batch/slurm/slurm.mustache
psij/launchers/__init__.py
psij/launchers/aprun.py
psij/launchers/jsrun.py
psij/launchers/mpirun.py
psij/launchers/multiple.py
psij/launchers/script_based_launcher.py
psij/launchers/single.py
psij/launchers/srun.py
psij/launchers/scripts/__init__.py
psij/launchers/scripts/aprun_launch.sh
psij/launchers/scripts/jsrun_launch.sh
psij/launchers/scripts/launcher_lib.sh
psij/launchers/scripts/mpi_launch.sh
psij/launchers/scripts/multi_launch.sh
psij/launchers/scripts/single_launch.sh
psij/launchers/scripts/srun_launch.sh
psij-descriptors/aprun_descriptor.py
psij-descriptors/cobalt_descriptor.py
psij-descriptors/core_descriptors.py
psij-descriptors/flux_descriptor.py
psij-descriptors/jsrun_descriptor.py
psij-descriptors/lsf_descriptor.py
psij-descriptors/pbs_descriptor.py
psij-descriptors/rp_descriptor.py
psij-descriptors/slurm_descriptor.py
psij-descriptors/srun_descriptor.py
psij_python-0.9.11.dist-info/LICENSE
psij_python-0.9.11.dist-info/METADATA
psij_python-0.9.11.dist-info/WHEEL
psij_python-0.9.11.dist-info/top_level.txt
psij_python-0.9.11.dist-info/RECORD
