Metadata-Version: 2.1
Name: psij-python
Version: 0.9.11
Summary: This is an implementation of the PSI/J (Portable Submission Interface for Jobs) specification.
Home-page: https://github.com/exaworks/psij-python
Author: The ExaWorks Team
Author-email: hategan@mcs.anl.gov
Classifier: Programming Language :: Python :: 3
Classifier: License :: OSI Approved :: MIT License
Requires-Python: >=3.8
License-File: LICENSE
Requires-Dist: packaging <=25.0,>=24.0
Requires-Dist: psutil <=7.0.0,>=5.9
Requires-Dist: pystache >=0.6.0
Requires-Dist: typeguard >=3.0.1
